viber/__init__.py
viber/bot/__init__.py
viber/bot/api.py
viber/bot/base.py
viber/bot/bot.py
viber/buttons.py
viber/config.py
viber/contrib/__init__.py
viber/contrib/fsm_storage/__init__.py
viber/contrib/fsm_storage/mongo.py
viber/dispatcher/__init__.py
viber/dispatcher/dispatcher.py
viber/dispatcher/filters/__init__.py
viber/dispatcher/filters/builtin.py
viber/dispatcher/filters/factory.py
viber/dispatcher/filters/filters.py
viber/dispatcher/filters/state.py
viber/dispatcher/handler.py
viber/dispatcher/storage.py
viber/dispatcher/webhook.py
viber/helpers.py
viber/keyboards.py
viber/loader.py
viber/types/__init__.py
viber/types/base.py
viber/types/callback_query.py
viber/types/contact.py
viber/types/conversation_started.py
viber/types/fields.py
viber/types/inline_keyboard.py
viber/types/message.py
viber/types/message_id.py
viber/types/reply_keyboard.py
viber/types/update.py
viber/types/user.py
viber/utils/__init__.py
viber/utils/deprecated.py
viber/utils/exceptions.py
viber/utils/helper.py
viber/utils/payload.py
async_viber-0.4.0.dist-info/WHEEL
async_viber-0.4.0.dist-info/METADATA
async_viber-0.4.0.dist-info/RECORD
