Metadata-Version: 2.1
Name: async-viber
Version: 0.4.0
License: MIT
Author-email: levch <levchenko.d.a1998@gmail.com>
Requires-Python: >=3.10
Requires-Dist: aiogram>=2.25.1
Requires-Dist: motor>=3.1.2
Requires-Dist: parsenv>=0.1.3
